{
  "project_info": {
    "project_number": "977841302259",
    "project_id": "cinemon-edce3",
    "storage_bucket": "cinemon-edce3.appspot.com"
  },
  "client": [
    {
      "client_info": {
        "mobilesdk_app_id": "1:977841302259:android:6f2f4ac911607a9d566586",
        "android_client_info": {
          "package_name": "com.example.cinemon"
        }
      },
      "oauth_client": [
        {
          "client_id": "977841302259-u8s0t9djr4u6enjhr1kurkoa8iq7gik7.apps.googleusercontent.com",
          "client_type": 3
        }
      ],
      "api_key": [
        {
          "current_key": "AIzaSyDCmEJOTlz1eJ5YqwLxv8fth-6y3_VNNnE"
        }
      ],
      "services": {
        "appinvite_service": {
          "other_platform_oauth_client": [
            {
              "client_id": "977841302259-u8s0t9djr4u6enjhr1kurkoa8iq7gik7.apps.googleusercontent.com",
              "client_type": 3
            }
          ]
        }
      }
    }
  ],
  "configuration_version": "1"
}